plasmidsaurus_helper/__init__.py
plasmidsaurus_helper/main.py
plasmidsaurus_helper-0.2.dist-info/METADATA
plasmidsaurus_helper-0.2.dist-info/WHEEL
plasmidsaurus_helper-0.2.dist-info/entry_points.txt
plasmidsaurus_helper-0.2.dist-info/top_level.txt
plasmidsaurus_helper-0.2.dist-info/RECORD
